{
  "users": [
    {
      "id": 1,
      "fname": "Reza",
      "lname": "Naseri",
      "email": "reza@gmail.com",
      "pass": "123456",
      "login": ""
    },
    {
      "email": "reza@gmail.com",
      "pass": "123456",
      "id": 2
    },
    {
      "email": "reza@gmail.com",
      "pass": "123456",
      "id": 3
    },
    {
      "email": "svsvsv@gmail.com",
      "pass": "rvfsavaVsdv",
      "id": 4
    },
    {
      "email": "svsvsv@gmail.com",
      "pass": "rvfsavaVsdv",
      "id": 5
    },
    {
      "email": "svsvsv@gmail.com",
      "pass": "rvfsavaVsdv",
      "id": 6
    },
    {
      "email": "reza@gmail.com",
      "pass": "123456",
      "id": 7
    },
    {
      "email": "reza@gmail.com",
      "pass": "123456",
      "id": 8
    },
    {
      "email": "reza@gmail.com",
      "pass": "123456",
      "id": 9
    },
    {
      "email": "reza@gmail.com",
      "pass": "123456",
      "id": 10
    },
    {
      "email": "reza@gmail.com",
      "pass": "123456",
      "id": 11
    },
    {
      "email": "reza@gmail.com",
      "pass": "123456",
      "id": 12
    },
    {
      "email": "reza@gmail.com",
      "pass": "123456",
      "id": 13
    },
    {
      "email": "reza@gmail.com",
      "pass": "123456",
      "id": 14
    },
    {
      "params": {
        "fname": "shadi",
        "lname": "ghaffarvand",
        "email": "shadi@go2tr.com",
        "pass": "123456"
      },
      "id": 15
    },
    {
      "params": {
        "fname": "shadi",
        "lname": "ghaffarvand",
        "email": "shadi@go2tr.com",
        "pass": "123456"
      },
      "id": 16
    },
    {
      "fname": "shadi",
      "lname": "ghaffarvand",
      "email": "shadi@go2tr.com",
      "pass": "123456",
      "id": 17
    },
    {
      "fname": "shadi",
      "lname": "ghaffarvand",
      "email": "shadi@go2tr.com",
      "pass": "123456",
      "id": 18
    },
    {
      "fname": "shadi",
      "lname": "ghaffarvand",
      "email": "shadi@go2tr.com",
      "pass": "123456",
      "id": 19
    },
    {
      "fname": "shadi",
      "lname": "ghaffarvand",
      "email": "shadi@go2tr.com",
      "pass": "123456",
      "id": 20
    },
    {
      "fname": "shadi",
      "lname": "ghaffarvand",
      "email": "shadi@go2tr.com",
      "pass": "123456",
      "id": 21
    },
    {
      "fname": "shadi",
      "lname": "ghaffarvand",
      "email": "shadi@go2tr.com",
      "pass": "123456",
      "id": 22
    },
    {
      "fname": "shadi",
      "lname": "ghaffarvand",
      "email": "shadi@go2tr.com",
      "pass": "123456",
      "id": 23
    },
    {
      "fname": "shadi",
      "lname": "ghaffarvand",
      "email": "shadi@go2tr.com",
      "pass": "123456",
      "id": 24
    },
    {
      "fname": "shadi",
      "lname": "ghaffarvand",
      "email": "shadi@go2tr.com",
      "pass": "123456",
      "id": 25
    },
    {
      "fname": "shadi",
      "lname": "ghaffarvand",
      "email": "tina.hosseinpour@go2tr.com",
      "pass": "123",
      "id": 26
    },
    {
      "fname": "shadi",
      "lname": "ghaffarvand",
      "email": "tina.hosseinpour@go2tr.com",
      "pass": "46",
      "id": 27
    },
    {
      "fname": "shadi",
      "lname": "ghaffarvand",
      "email": "tina.hosseinpour@go2tr.com",
      "pass": "46",
      "id": 28
    },
    {
      "fname": "shadi",
      "lname": "ghaffarvand",
      "email": "tina.hosseinpour@go2tr.com",
      "pass": "46",
      "id": 29
    },
    {
      "fname": "shadi",
      "lname": "ghaffarvand",
      "email": "tina.hosseinpour@go2tr.com",
      "pass": "252",
      "id": 30
    },
    {
      "fname": "shadi",
      "lname": "ghaffarvand",
      "email": "shadi@go2tr.com",
      "pass": "123",
      "id": 31
    },
    {
      "fname": "shadi",
      "lname": "ghaffarvand",
      "email": "shadi@go2tr.com",
      "pass": "123",
      "id": 32
    },
    {
      "fname": "shadi",
      "lname": "ghaffarvand",
      "email": "shadi@go2tr.com",
      "pass": "123",
      "id": 33
    },
    {
      "fname": "shadi",
      "lname": "ghaffarvand",
      "email": "shdvdvfadi@go2tr.com",
      "pass": "123",
      "id": 34
    },
    {
      "fname": "sdvhadi",
      "lname": "ghaffarvand",
      "email": "shdvdvfadi@go2tr.com",
      "pass": "123",
      "id": 35
    },
    {
      "fname": "sdvhadi",
      "lname": "ghdvfvaffarvand",
      "email": "shdvdvfadi@go2tr.com",
      "pass": "123dfv df",
      "id": 36
    },
    {
      "fname": "sdvhadi",
      "lname": "ghdvfvaffarvand",
      "email": "shdvdvfadi@go2tr.com",
      "pass": "123dfv df",
      "id": 37
    },
    {
      "fname": "shadi",
      "lname": "ghaffarvand",
      "email": "shadi@go2tr.com",
      "pass": "123",
      "id": 38
    },
    {
      "fname": "رضا",
      "lname": "ناصری",
      "email": "rnaserivand@gmail.com",
      "pass": "123456",
      "id": 39
    },
    {
      "fname": "dvdfv",
      "lname": "vdf",
      "email": "wwwswv@gmail.com",
      "pass": "123",
      "repass": "123",
      "id": 40
    },
    {
      "fname": "رضا",
      "lname": "ناصری وند",
      "email": "rnaseri@gmail.com",
      "pass": "147852",
      "repass": "147852",
      "id": 41
    }
  ]
}